<?xml version="1.0" encoding="utf-8"?>
<Fragment>
	<SpellDef InternalName="BMB_SummonLupus">
        <DisplayName>Summon Lupus</DisplayName>
        <Description>Smmon a random level 8 Canine Friend</Description>
        <Image>M_Warg_PlainsWarg_Card.png</Image>
        <IconFG>BMB_Ability_SummonLupus.png</IconFG>
		<CanStack>0</CanStack>
        <Cooldown>8</Cooldown>
        <SpellBookSortCategory>Summon</SpellBookSortCategory>
        <SpellBookSortSubCategory>Summon</SpellBookSortSubCategory>
        <SpellType>Tactical</SpellType>
        <SpellClass>Offensive</SpellClass>
        <SpellSubClass>Summon</SpellSubClass>
        <SpellTargetType>EmptyTile</SpellTargetType>
        <HideInHiergamenon>1</HideInHiergamenon>
		<AppliesRandomModifier>1</AppliesRandomModifier>
        <IsSpecialAbility>1</IsSpecialAbility>
		<SpellResourceCost>
            <Resource>Mana</Resource>
            <Amount>10</Amount>
        </SpellResourceCost>
		<GameModifier>
            <ModType>Unit</ModType>
            <Attribute>SummonUnit</Attribute>
            <UnitClass>Wolf_Group</UnitClass>
            <Duration>-1</Duration>
            <Calculate InternalName="Calc" ValueOwner="CastingUnit">
                <Expression><![CDATA[[UnitStat_BonusSummonLevel] + 8]]></Expression>
            </Calculate>
            <Calculate InternalName="Value">
                <Expression><![CDATA[[Calc]]]></Expression>
            </Calculate>
        </GameModifier>
		<GameModifier>
            <ModType>Unit</ModType>
            <Attribute>SummonUnit</Attribute>
            <UnitClass>Wolf_Group</UnitClass>
            <Duration>-1</Duration>
            <Calculate InternalName="Calc" ValueOwner="CastingUnit">
                <Expression><![CDATA[[UnitStat_BonusSummonLevel] + 8]]></Expression>
            </Calculate>
            <Calculate InternalName="Value">
                <Expression><![CDATA[[Calc]]]></Expression>
            </Calculate>
        </GameModifier>
		<GameModifier>
            <ModType>Unit</ModType>
            <Attribute>SummonUnit</Attribute>
            <UnitClass>GreatWolf</UnitClass>
            <Duration>-1</Duration>
            <Calculate InternalName="Calc" ValueOwner="CastingUnit">
                <Expression><![CDATA[[UnitStat_BonusSummonLevel] + 8]]></Expression>
            </Calculate>
            <Calculate InternalName="Value">
                <Expression><![CDATA[[Calc]]]></Expression>
            </Calculate>
        </GameModifier>
		<GameModifier>
            <ModType>Unit</ModType>
            <Attribute>SummonUnit</Attribute>
            <UnitClass>EbbenWolf</UnitClass>
            <Duration>-1</Duration>
            <Calculate InternalName="Calc" ValueOwner="CastingUnit">
                <Expression><![CDATA[[UnitStat_BonusSummonLevel] + 8]]></Expression>
            </Calculate>
            <Calculate InternalName="Value">
                <Expression><![CDATA[[Calc]]]></Expression>
            </Calculate>
        </GameModifier>
		<GameModifier>
            <ModType>Unit</ModType>
            <Attribute>SummonUnit</Attribute>
            <UnitClass>AnnieDog</UnitClass>
            <Duration>-1</Duration>
            <Calculate InternalName="Calc" ValueOwner="CastingUnit">
                <Expression><![CDATA[[UnitStat_BonusSummonLevel] + 8]]></Expression>
            </Calculate>
            <Calculate InternalName="Value">
                <Expression><![CDATA[[Calc]]]></Expression>
            </Calculate>
        </GameModifier>
		<GameModifier>
            <ModType>Unit</ModType>
            <Attribute>SummonUnit</Attribute>
            <UnitClass>TimberWarg</UnitClass>
            <Duration>-1</Duration>
            <Calculate InternalName="Calc" ValueOwner="CastingUnit">
                <Expression><![CDATA[[UnitStat_BonusSummonLevel] + 8]]></Expression>
            </Calculate>
            <Calculate InternalName="Value">
                <Expression><![CDATA[[Calc]]]></Expression>
            </Calculate>
        </GameModifier>
		<GameModifier>
            <ModType>Unit</ModType>
            <Attribute>SummonUnit</Attribute>
            <UnitClass>ShadowWarg</UnitClass>
            <Duration>-1</Duration>
            <Calculate InternalName="Calc" ValueOwner="CastingUnit">
                <Expression><![CDATA[[UnitStat_BonusSummonLevel] + 8]]></Expression>
            </Calculate>
            <Calculate InternalName="Value">
                <Expression><![CDATA[[Calc]]]></Expression>
            </Calculate>
        </GameModifier>
        <GameModifier>
            <ModType>Unit</ModType>
            <Attribute>SummonUnit</Attribute>
            <UnitClass>IceWarg</UnitClass>
            <Duration>-1</Duration>
            <Calculate InternalName="Calc" ValueOwner="CastingUnit">
                <Expression><![CDATA[[UnitStat_BonusSummonLevel] + 8]]></Expression>
            </Calculate>
            <Calculate InternalName="Value">
                <Expression><![CDATA[[Calc]]]></Expression>
            </Calculate>
        </GameModifier>		
        <AIData AIPersonality="AI_General">
            <AIPriority>50</AIPriority>
        </AIData>
        <HitSoundFX>Spell_Howl_01</HitSoundFX>
        <SpellDefEffect>
            <EffectName>S_SummonEarthElemental_Particle</EffectName>
            <LocalPosition>0,0,0</LocalPosition>
            <EffectScale>0.5</EffectScale>
            <EffectDelay>0</EffectDelay>
            <SnapToTerrain>1</SnapToTerrain>
        </SpellDefEffect>
    </SpellDef>
</Fragment>
